{"cameraMode":{"drawMode":0,"name":"Shaded","section":"Shading Mode"},"sceneLighting":true,"audioPlay":false,"sceneViewState":{"m_AlwaysRefresh":false,"showFog":true,"showSkybox":true,"showFlares":true,"showImageEffects":true,"showParticleSystems":true,"showVisualEffectGraphs":true,"m_FxEnabled":true},"in2DMode":false,"pivot":{"x":0.08685493469238281,"y":-0.027188777923583986,"z":-0.06682825088500977},"rotation":{"x":-0.08645875006914139,"y":0.9014925956726074,"z":-0.21232426166534425,"w":-0.3670891225337982},"size":3.740349531173706,"orthographic":false}